{"assets":{"D7A57E6336E985CA49FE92A402E63D79":{"type":"texture","index":8,"url":{"native":"assets\/2AB16022-C672-4F15-A5E2-95BCBE91B563.pdf"},"width":999,"height":562},"C4647098179AB1AAB4337D365019E619":{"type":"texture","index":7,"url":{"native":"assets\/2AB16022-C672-4F15-A5E2-95BCBE91B563.pdf"},"width":998.46417236328125,"height":561.6361083984375},"A34FD3F593A6EDCE801E2834DFD2FC94":{"type":"texture","index":6,"url":{"native":"assets\/2AB16022-C672-4F15-A5E2-95BCBE91B563.pdf"},"width":999,"height":562},"mudanza1.gif-0.0000-2.7600":{"type":"video","index":0,"url":{"web":"assets\/mudanza1.gif-0.0000-2.7600.gif","native":"assets\/mudanza1.gif-0.0000-2.7600.gif"},"width":1280,"height":720},"D1696C2D9FEE05E3DF8E2DB583B716F7":{"type":"texture","index":1,"url":{"native":"assets\/2AB16022-C672-4F15-A5E2-95BCBE91B563.pdf"},"width":999,"height":562},"17DCB991082C7F26E78BF0DA1454917A":{"type":"texture","index":4,"url":{"native":"assets\/2AB16022-C672-4F15-A5E2-95BCBE91B563.pdf"},"width":15,"height":47},"C25C25FF361FB24FC35F6B120D2F252D":{"type":"texture","index":0,"url":{"native":"assets\/2AB16022-C672-4F15-A5E2-95BCBE91B563.pdf"},"width":1920,"height":1080},"mudanza2.gif-0.0000-2.1300":{"type":"video","index":0,"url":{"web":"assets\/mudanza2.gif-0.0000-2.1300.gif","native":"assets\/mudanza2.gif-0.0000-2.1300.gif"},"width":1280,"height":720},"43FB4D82A5EE442AD49CC5999A83B19F":{"type":"texture","index":9,"url":{"native":"assets\/2AB16022-C672-4F15-A5E2-95BCBE91B563.pdf"},"width":998.46417236328125,"height":561.6361083984375},"6191C09AD367DBB5DEF99C2F9AB7298E":{"type":"texture","index":5,"url":{"native":"assets\/2AB16022-C672-4F15-A5E2-95BCBE91B563.pdf"},"width":16,"height":83},"934183F23C3F2117C7E70140ABEA59E6":{"type":"texture","index":2,"url":{"native":"assets\/2AB16022-C672-4F15-A5E2-95BCBE91B563.pdf"},"width":1421,"height":23},"F3E2BF57DBBA357EBFD39D6787D71648":{"type":"texture","index":3,"url":{"native":"assets\/2AB16022-C672-4F15-A5E2-95BCBE91B563.pdf"},"width":999,"height":562},"6A3B082A2ABCE3326AD9F0AF8CC0CB0A":{"type":"texture","index":10,"url":{"native":"assets\/2AB16022-C672-4F15-A5E2-95BCBE91B563.pdf"},"width":1920,"height":1080},"700DB36790A0A0B19C6FC75F06CE45BB":{"type":"texture","index":11,"url":{"native":"assets\/2AB16022-C672-4F15-A5E2-95BCBE91B563.pdf"},"width":1920,"height":1080}},"events":[{"effects":[{"beginTime":0,"baseLayer":{"animations":[],"initialState":{"affineTransform":[1,0,0,1,0,0],"masksToBounds":false,"rotation":0,"scale":1,"position":{"pointX":1429.8421630859375,"pointY":523.44490051269531},"width":999,"sublayerTransform":[1,0,0,0,0,1,0,0,0,0,1,0,0,0,0,1],"contentsRect":{"y":0,"x":0,"width":1,"height":1},"opacity":1,"edgeAntialiasingMask":251658240,"height":562,"hidden":false,"anchorPoint":{"pointX":0.5,"pointY":0.5}},"objectID":"3C98D31F-A8A9-4565-936B-2D0379F4E9A0","layers":[{"animations":[],"initialState":{"affineTransform":[1,0,0,1,0,0],"masksToBounds":false,"rotation":0,"scale":1,"position":{"pointX":29.6578369140625,"pointY":297.55509948730469},"width":999,"sublayerTransform":[1,0,0,0,0,1,0,0,0,0,1,-0.00035007912466775983,0,0,0,1],"contentsRect":{"y":0,"x":0,"width":1,"height":1},"opacity":1,"edgeAntialiasingMask":251658240,"height":562,"hidden":false,"anchorPoint":{"pointX":0.029687524438501003,"pointY":0.52945747239733931}},"layers":[{"animations":[{"additive":false,"timeOffset":0,"beginTime":1e-100,"repeatCount":0,"fillMode":"both","duration":0.01,"autoreverses":false,"animations":[{"additive":false,"timeOffset":0,"beginTime":0,"from":{"scalar":false},"repeatCount":0,"fillMode":"removed","duration":0.01,"autoreverses":false,"property":"hidden","to":{"scalar":false},"removedOnCompletion":true},{"additive":false,"timeOffset":0,"beginTime":0,"from":{"scalar":true},"repeatCount":0,"fillMode":"removed","duration":0.01,"autoreverses":false,"property":"isPlaying","to":{"scalar":true},"removedOnCompletion":true}],"removedOnCompletion":false}],"layers":[],"texturedRectangle":{"isBackgroundTexture":true,"singleTextureOpacity":1,"textureType":5,"textBaseline":0,"textXHeight":0,"isVerticalText":false},"initialState":{"affineTransform":[1,0,0,1,0,0],"masksToBounds":false,"rotation":0,"scale":1,"position":{"pointX":499.1578369140625,"pointY":280.55509948730469},"width":999,"sublayerTransform":[1,0,0,0,0,1,0,0,0,0,1,0,0,0,0,1],"contentsRect":{"y":0,"x":0,"width":1,"height":1},"opacity":1,"edgeAntialiasingMask":0,"height":562,"hidden":false,"anchorPoint":{"pointX":0.5,"pointY":0.5}},"texture":"D1696C2D9FEE05E3DF8E2DB583B716F7"}]}]},"effects":[{"beginTime":0,"baseLayer":{"animations":[],"initialState":{"affineTransform":[1,0,0,1,0,0],"masksToBounds":false,"rotation":0,"scale":1,"position":{"pointX":1429.5742492675781,"pointY":523.26295471191406},"width":998.46417236328125,"sublayerTransform":[1,0,0,0,0,1,0,0,0,0,1,0,0,0,0,1],"contentsRect":{"y":0,"x":0,"width":1,"height":1},"opacity":1,"edgeAntialiasingMask":251658240,"height":561.6361083984375,"hidden":false,"anchorPoint":{"pointX":0.5,"pointY":0.5}},"objectID":"3C98D31F-A8A9-4565-936B-2D0379F4E9A0","layers":[{"animations":[],"layers":[],"texturedRectangle":{"isBackgroundTexture":true,"singleTextureOpacity":1,"textureType":5,"textBaseline":0,"textXHeight":0,"isVerticalText":false},"initialState":{"affineTransform":[1,0,0,1,0,0],"masksToBounds":false,"rotation":0,"scale":1,"position":{"pointX":499.1578369140625,"pointY":280.55509948730469},"width":999,"sublayerTransform":[1,0,0,0,0,1,0,0,0,0,1,0,0,0,0,1],"contentsRect":{"y":0,"x":0,"width":1,"height":1},"opacity":1,"edgeAntialiasingMask":0,"height":562,"hidden":true,"anchorPoint":{"pointX":0.5,"pointY":0.5}},"texture":"A34FD3F593A6EDCE801E2834DFD2FC94"},{"animations":[],"layers":[],"isVideoLayer":true,"initialState":{"affineTransform":[1,0,0,1,0,0],"masksToBounds":false,"rotation":0,"scale":1,"position":{"pointX":499.23208618164062,"pointY":280.81805419921875},"width":998.46417236328125,"sublayerTransform":[1,0,0,0,0,1,0,0,0,0,1,0,0,0,0,1],"contentsRect":{"y":0,"x":0,"width":1,"height":1},"opacity":1,"edgeAntialiasingMask":251658240,"height":561.6361083984375,"hidden":false,"anchorPoint":{"pointX":0.5,"pointY":0.5}},"texture":"C4647098179AB1AAB4337D365019E619"}]},"effects":[],"movie":{"volume":1,"isStreaming":false,"isAudioOnly":false,"endTime":2.130000114440918,"startTime":0,"asset":"mudanza2.gif-0.0000-2.1300","loopMode":"looping"},"duration":0,"type":"buildIn","attributes":{"direction":0},"name":"renderMovie","objectID":"3C98D31F-A8A9-4565-936B-2D0379F4E9A0"},{"beginTime":0,"baseLayer":{"animations":[],"initialState":{"affineTransform":[1,0,0,1,0,0],"masksToBounds":false,"rotation":0,"scale":1,"position":{"pointX":442.77656555175781,"pointY":523.44490051269531},"width":999,"sublayerTransform":[1,0,0,0,0,1,0,0,0,0,1,0,0,0,0,1],"contentsRect":{"y":0,"x":0,"width":1,"height":1},"opacity":1,"edgeAntialiasingMask":251658240,"height":562,"hidden":false,"anchorPoint":{"pointX":0.5,"pointY":0.5}},"objectID":"9F44D0F1-E2FB-4D4F-A47F-9CB5EC20381A","layers":[{"animations":[],"initialState":{"affineTransform":[1,0,0,1,0,0],"masksToBounds":false,"rotation":0,"scale":1,"position":{"pointX":1016.7234344482422,"pointY":297.55509948730469},"width":999,"sublayerTransform":[1,0,0,0,0,1,0,0,0,0,1,-0.00035007912466775983,0,0,0,1],"contentsRect":{"y":0,"x":0,"width":1,"height":1},"opacity":1,"edgeAntialiasingMask":251658240,"height":562,"hidden":false,"anchorPoint":{"pointX":1.0177411756238661,"pointY":0.52945747239733931}},"layers":[{"animations":[{"additive":false,"timeOffset":0,"beginTime":1e-100,"repeatCount":0,"fillMode":"both","duration":0.01,"autoreverses":false,"animations":[{"additive":false,"timeOffset":0,"beginTime":0,"from":{"scalar":false},"repeatCount":0,"fillMode":"removed","duration":0.01,"autoreverses":false,"property":"hidden","to":{"scalar":false},"removedOnCompletion":true},{"additive":false,"timeOffset":0,"beginTime":0,"from":{"scalar":true},"repeatCount":0,"fillMode":"removed","duration":0.01,"autoreverses":false,"property":"isPlaying","to":{"scalar":true},"removedOnCompletion":true}],"removedOnCompletion":false}],"layers":[],"texturedRectangle":{"isBackgroundTexture":true,"singleTextureOpacity":1,"textureType":5,"textBaseline":0,"textXHeight":0,"isVerticalText":false},"initialState":{"affineTransform":[1,0,0,1,0,0],"masksToBounds":false,"rotation":0,"scale":1,"position":{"pointX":499.22343444824219,"pointY":280.55509948730469},"width":999,"sublayerTransform":[1,0,0,0,0,1,0,0,0,0,1,0,0,0,0,1],"contentsRect":{"y":0,"x":0,"width":1,"height":1},"opacity":1,"edgeAntialiasingMask":0,"height":562,"hidden":false,"anchorPoint":{"pointX":0.5,"pointY":0.5}},"texture":"F3E2BF57DBBA357EBFD39D6787D71648"}]}]},"effects":[{"beginTime":0,"baseLayer":{"animations":[],"initialState":{"affineTransform":[1,0,0,1,0,0],"masksToBounds":false,"rotation":0,"scale":1,"position":{"pointX":442.50865173339844,"pointY":523.26295471191406},"width":998.46417236328125,"sublayerTransform":[1,0,0,0,0,1,0,0,0,0,1,0,0,0,0,1],"contentsRect":{"y":0,"x":0,"width":1,"height":1},"opacity":1,"edgeAntialiasingMask":251658240,"height":561.6361083984375,"hidden":false,"anchorPoint":{"pointX":0.5,"pointY":0.5}},"objectID":"9F44D0F1-E2FB-4D4F-A47F-9CB5EC20381A","layers":[{"animations":[],"layers":[],"texturedRectangle":{"isBackgroundTexture":true,"singleTextureOpacity":1,"textureType":5,"textBaseline":0,"textXHeight":0,"isVerticalText":false},"initialState":{"affineTransform":[1,0,0,1,0,0],"masksToBounds":false,"rotation":0,"scale":1,"position":{"pointX":499.22343444824219,"pointY":280.55509948730469},"width":999,"sublayerTransform":[1,0,0,0,0,1,0,0,0,0,1,0,0,0,0,1],"contentsRect":{"y":0,"x":0,"width":1,"height":1},"opacity":1,"edgeAntialiasingMask":0,"height":562,"hidden":true,"anchorPoint":{"pointX":0.5,"pointY":0.5}},"texture":"D7A57E6336E985CA49FE92A402E63D79"},{"animations":[],"layers":[],"isVideoLayer":true,"initialState":{"affineTransform":[1,0,0,1,0,0],"masksToBounds":false,"rotation":0,"scale":1,"position":{"pointX":499.23208618164062,"pointY":280.81805419921875},"width":998.46417236328125,"sublayerTransform":[1,0,0,0,0,1,0,0,0,0,1,0,0,0,0,1],"contentsRect":{"y":0,"x":0,"width":1,"height":1},"opacity":1,"edgeAntialiasingMask":251658240,"height":561.6361083984375,"hidden":false,"anchorPoint":{"pointX":0.5,"pointY":0.5}},"texture":"43FB4D82A5EE442AD49CC5999A83B19F"}]},"effects":[],"movie":{"volume":1,"isStreaming":false,"isAudioOnly":false,"endTime":2.7599999904632568,"startTime":0,"asset":"mudanza1.gif-0.0000-2.7600","loopMode":"looping"},"duration":0,"type":"buildIn","attributes":{"direction":0},"name":"renderMovie","objectID":"9F44D0F1-E2FB-4D4F-A47F-9CB5EC20381A"}],"duration":0.01,"type":"buildIn","attributes":{"direction":0},"name":"apple:movie-start","objectID":"9F44D0F1-E2FB-4D4F-A47F-9CB5EC20381A"}],"duration":0.01,"type":"buildIn","attributes":{"direction":0},"name":"apple:movie-start","objectID":"3C98D31F-A8A9-4565-936B-2D0379F4E9A0"}],"automaticPlay":true,"hyperlinks":[],"accessibility":[{"text":"SWAN","targetRectangle":{"y":17.811520528793331,"x":1887.6313705444336,"width":17.564895629882812,"height":44.925000000000004}},{"text":"GRANDPA quickly joins her to help out and we see them both, sleeves rolled up, carrying the planter to its new corner.as the DAUGHTER unboxes some living room decor.","targetRectangle":{"y":1019.7887272834778,"x":250.41001105308533,"width":1419.1799999999987,"height":23.41986083984375}},{"text":"Rebolución","targetRectangle":{"y":981.11347107887264,"x":1887.6313705444336,"width":17.564895629882812,"height":81.075000000000045}}],"baseLayer":{"animations":[],"initialState":{"affineTransform":[1,0,0,1,0,0],"masksToBounds":false,"rotation":0,"scale":1,"position":{"pointX":960,"pointY":540},"width":1920,"sublayerTransform":[1,0,0,0,0,1,0,0,0,0,1,0,0,0,0,1],"contentsRect":{"y":0,"x":0,"width":1,"height":1},"opacity":1,"edgeAntialiasingMask":251658240,"height":1080,"hidden":false,"anchorPoint":{"pointX":0.5,"pointY":0.5}},"layers":[{"animations":[],"initialState":{"affineTransform":[1,0,0,1,0,0],"masksToBounds":false,"rotation":0,"scale":1,"position":{"pointX":960,"pointY":540},"width":1920,"sublayerTransform":[1,0,0,0,0,1,0,0,0,0,1,0,0,0,0,1],"contentsRect":{"y":0,"x":0,"width":1,"height":1},"opacity":1,"edgeAntialiasingMask":251658240,"height":1080,"hidden":false,"anchorPoint":{"pointX":0.5,"pointY":0.5}},"layers":[{"animations":[],"initialState":{"affineTransform":[1,0,0,1,0,0],"masksToBounds":false,"rotation":0,"scale":1,"position":{"pointX":960,"pointY":540},"width":1920,"sublayerTransform":[1,0,0,0,0,1,0,0,0,0,1,0,0,0,0,1],"contentsRect":{"y":0,"x":0,"width":1,"height":1},"opacity":1,"edgeAntialiasingMask":251658240,"height":1080,"hidden":false,"anchorPoint":{"pointX":0.5,"pointY":0.5}},"layers":[{"animations":[],"layers":[],"texturedRectangle":{"isBackgroundTexture":true,"singleTextureOpacity":1,"textureType":1,"textBaseline":0,"textXHeight":0,"isVerticalText":false},"initialState":{"affineTransform":[1,0,0,1,0,0],"masksToBounds":false,"rotation":0,"scale":1,"position":{"pointX":960,"pointY":540},"width":1920,"sublayerTransform":[1,0,0,0,0,1,0,0,0,0,1,0,0,0,0,1],"contentsRect":{"y":0,"x":0,"width":1,"height":1},"opacity":1,"edgeAntialiasingMask":0,"height":1080,"hidden":false,"anchorPoint":{"pointX":0.5,"pointY":0.5}},"texture":"C25C25FF361FB24FC35F6B120D2F252D"}]}]},{"animations":[],"initialState":{"affineTransform":[1,0,0,1,0,0],"masksToBounds":false,"rotation":0,"scale":1,"position":{"pointX":960,"pointY":540},"width":1920,"sublayerTransform":[1,0,0,0,0,1,0,0,0,0,1,0,0,0,0,1],"contentsRect":{"y":0,"x":0,"width":1,"height":1},"opacity":1,"edgeAntialiasingMask":251658240,"height":1080,"hidden":false,"anchorPoint":{"pointX":0.5,"pointY":0.5}},"layers":[{"animations":[],"initialState":{"affineTransform":[1,0,0,1,0,0],"masksToBounds":false,"rotation":0,"scale":1,"position":{"pointX":1429.8421630859375,"pointY":523.44490051269531},"width":999,"sublayerTransform":[1,0,0,0,0,1,0,0,0,0,1,0,0,0,0,1],"contentsRect":{"y":0,"x":0,"width":1,"height":1},"opacity":1,"edgeAntialiasingMask":251658240,"height":562,"hidden":false,"anchorPoint":{"pointX":0.5,"pointY":0.5}},"objectID":"3C98D31F-A8A9-4565-936B-2D0379F4E9A0","layers":[{"animations":[],"layers":[],"texturedRectangle":{"isBackgroundTexture":true,"singleTextureOpacity":1,"textureType":5,"textBaseline":0,"textXHeight":0,"isVerticalText":false},"initialState":{"affineTransform":[1,0,0,1,0,0],"masksToBounds":false,"rotation":0,"scale":1,"position":{"pointX":499.1578369140625,"pointY":280.55509948730469},"width":999,"sublayerTransform":[1,0,0,0,0,1,0,0,0,0,1,0,0,0,0,1],"contentsRect":{"y":0,"x":0,"width":1,"height":1},"opacity":1,"edgeAntialiasingMask":0,"height":562,"hidden":false,"anchorPoint":{"pointX":0.5,"pointY":0.5}},"texture":"D1696C2D9FEE05E3DF8E2DB583B716F7"}]}]},{"animations":[],"initialState":{"affineTransform":[1,0,0,1,0,0],"masksToBounds":false,"rotation":0,"scale":1,"position":{"pointX":960,"pointY":540},"width":1920,"sublayerTransform":[1,0,0,0,0,1,0,0,0,0,1,0,0,0,0,1],"contentsRect":{"y":0,"x":0,"width":1,"height":1},"opacity":1,"edgeAntialiasingMask":251658240,"height":1080,"hidden":false,"anchorPoint":{"pointX":0.5,"pointY":0.5}},"layers":[{"animations":[],"initialState":{"affineTransform":[1,0,0,1,0,0],"masksToBounds":false,"rotation":0,"scale":1,"position":{"pointX":957.38778877258301,"pointY":1028.2665050029755},"width":1421,"sublayerTransform":[1,0,0,0,0,1,0,0,0,0,1,0,0,0,0,1],"contentsRect":{"y":0,"x":0,"width":1,"height":1},"opacity":1,"edgeAntialiasingMask":251658240,"height":23,"hidden":false,"anchorPoint":{"pointX":0.5,"pointY":0.5}},"layers":[{"animations":[],"layers":[],"texturedRectangle":{"singleTextureOpacity":1,"textXHeight":0.44695652173913042,"textBaseline":0.7368973649066427,"isBackgroundTexture":true,"isVerticalText":false,"textColor":[0,0,0,1],"textureType":6},"initialState":{"affineTransform":[1,0,0,1,0,0],"masksToBounds":false,"rotation":0,"scale":1,"position":{"pointX":712.61221122741699,"pointY":16.733494997024536},"width":1421,"sublayerTransform":[1,0,0,0,0,1,0,0,0,0,1,0,0,0,0,1],"contentsRect":{"y":0,"x":0,"width":1,"height":1},"opacity":1,"edgeAntialiasingMask":0,"height":23,"hidden":false,"anchorPoint":{"pointX":0.5,"pointY":0.5}},"texture":"934183F23C3F2117C7E70140ABEA59E6"}]}]},{"animations":[],"initialState":{"affineTransform":[1,0,0,1,0,0],"masksToBounds":false,"rotation":0,"scale":1,"position":{"pointX":960,"pointY":540},"width":1920,"sublayerTransform":[1,0,0,0,0,1,0,0,0,0,1,0,0,0,0,1],"contentsRect":{"y":0,"x":0,"width":1,"height":1},"opacity":1,"edgeAntialiasingMask":251658240,"height":1080,"hidden":false,"anchorPoint":{"pointX":0.5,"pointY":0.5}},"layers":[{"animations":[],"initialState":{"affineTransform":[1,0,0,1,0,0],"masksToBounds":false,"rotation":0,"scale":1,"position":{"pointX":442.77656555175781,"pointY":523.44490051269531},"width":999,"sublayerTransform":[1,0,0,0,0,1,0,0,0,0,1,0,0,0,0,1],"contentsRect":{"y":0,"x":0,"width":1,"height":1},"opacity":1,"edgeAntialiasingMask":251658240,"height":562,"hidden":false,"anchorPoint":{"pointX":0.5,"pointY":0.5}},"objectID":"9F44D0F1-E2FB-4D4F-A47F-9CB5EC20381A","layers":[{"animations":[],"layers":[],"texturedRectangle":{"isBackgroundTexture":true,"singleTextureOpacity":1,"textureType":5,"textBaseline":0,"textXHeight":0,"isVerticalText":false},"initialState":{"affineTransform":[1,0,0,1,0,0],"masksToBounds":false,"rotation":0,"scale":1,"position":{"pointX":499.22343444824219,"pointY":280.55509948730469},"width":999,"sublayerTransform":[1,0,0,0,0,1,0,0,0,0,1,0,0,0,0,1],"contentsRect":{"y":0,"x":0,"width":1,"height":1},"opacity":1,"edgeAntialiasingMask":0,"height":562,"hidden":false,"anchorPoint":{"pointX":0.5,"pointY":0.5}},"texture":"F3E2BF57DBBA357EBFD39D6787D71648"}]}]},{"animations":[],"initialState":{"affineTransform":[1,0,0,1,0,0],"masksToBounds":false,"rotation":0,"scale":1,"position":{"pointX":960,"pointY":540},"width":1920,"sublayerTransform":[1,0,0,0,0,1,0,0,0,0,1,0,0,0,0,1],"contentsRect":{"y":0,"x":0,"width":1,"height":1},"opacity":1,"edgeAntialiasingMask":251658240,"height":1080,"hidden":false,"anchorPoint":{"pointX":0.5,"pointY":0.5}},"layers":[{"animations":[],"initialState":{"affineTransform":[1,0,0,1,0,0],"masksToBounds":false,"rotation":0,"scale":1,"position":{"pointX":1892.1091482639313,"pointY":38.289298057556152},"width":15,"sublayerTransform":[1,0,0,0,0,1,0,0,0,0,1,0,0,0,0,1],"contentsRect":{"y":0,"x":0,"width":1,"height":1},"opacity":1,"edgeAntialiasingMask":251658240,"height":47,"hidden":false,"anchorPoint":{"pointX":0.5,"pointY":0.5}},"layers":[{"animations":[],"layers":[],"texturedRectangle":{"singleTextureOpacity":1,"textXHeight":0.16500000000000001,"textBaseline":0.32173377808104159,"isBackgroundTexture":true,"isVerticalText":false,"textColor":[0.70822423696517944,0.091325722634792328,0,1],"textureType":6},"initialState":{"affineTransform":[1,0,0,1,0,0],"masksToBounds":false,"rotation":0,"scale":1,"position":{"pointX":11.890851736068726,"pointY":25.710701942443848},"width":15,"sublayerTransform":[1,0,0,0,0,1,0,0,0,0,1,0,0,0,0,1],"contentsRect":{"y":0,"x":0,"width":1,"height":1},"opacity":1,"edgeAntialiasingMask":0,"height":47,"hidden":false,"anchorPoint":{"pointX":0.5,"pointY":0.5}},"texture":"17DCB991082C7F26E78BF0DA1454917A"}]}]},{"animations":[],"initialState":{"affineTransform":[1,0,0,1,0,0],"masksToBounds":false,"rotation":0,"scale":1,"position":{"pointX":960,"pointY":540},"width":1920,"sublayerTransform":[1,0,0,0,0,1,0,0,0,0,1,0,0,0,0,1],"contentsRect":{"y":0,"x":0,"width":1,"height":1},"opacity":1,"edgeAntialiasingMask":251658240,"height":1080,"hidden":false,"anchorPoint":{"pointX":0.5,"pointY":0.5}},"layers":[{"animations":[],"initialState":{"affineTransform":[1,0,0,1,0,0],"masksToBounds":false,"rotation":0,"scale":1,"position":{"pointX":1892.6091482639313,"pointY":1018.5912461280823},"width":16,"sublayerTransform":[1,0,0,0,0,1,0,0,0,0,1,0,0,0,0,1],"contentsRect":{"y":0,"x":0,"width":1,"height":1},"opacity":1,"edgeAntialiasingMask":251658240,"height":83,"hidden":false,"anchorPoint":{"pointX":0.5,"pointY":0.5}},"layers":[{"animations":[],"layers":[],"texturedRectangle":{"singleTextureOpacity":1,"textXHeight":0.093433734939759039,"textBaseline":0.17377636289022,"isBackgroundTexture":true,"isVerticalText":false,"textColor":[0.70822423696517944,0.091325722634792328,0,1],"textureType":6},"initialState":{"affineTransform":[1,0,0,1,0,0],"masksToBounds":false,"rotation":0,"scale":1,"position":{"pointX":11.390851736068726,"pointY":44.408753871917725},"width":16,"sublayerTransform":[1,0,0,0,0,1,0,0,0,0,1,0,0,0,0,1],"contentsRect":{"y":0,"x":0,"width":1,"height":1},"opacity":1,"edgeAntialiasingMask":0,"height":83,"hidden":false,"anchorPoint":{"pointX":0.5,"pointY":0.5}},"texture":"6191C09AD367DBB5DEF99C2F9AB7298E"}]}]}]}},{"effects":[{"beginTime":0,"baseLayer":{"animations":[],"initialState":{"affineTransform":[1,0,0,1,0,0],"masksToBounds":false,"rotation":0,"scale":1,"position":{"pointX":960,"pointY":540},"width":1920,"sublayerTransform":[1,0,0,0,0,1,0,0,0,0,1,0,0,0,0,1],"contentsRect":{"y":0,"x":0,"width":1,"height":1},"opacity":1,"edgeAntialiasingMask":251658240,"height":1080,"hidden":false,"anchorPoint":{"pointX":0.5,"pointY":0.5}},"objectID":"0","layers":[{"animations":[],"initialState":{"affineTransform":[1,0,0,1,0,0],"masksToBounds":false,"rotation":0,"scale":1,"position":{"pointX":960,"pointY":540},"width":1920,"sublayerTransform":[1,0,0,0,0,1,0,0,0,0,1,-0.00035007912466775983,0,0,0,1],"contentsRect":{"y":0,"x":0,"width":1,"height":1},"opacity":1,"edgeAntialiasingMask":251658240,"height":1080,"hidden":false,"anchorPoint":{"pointX":0.5,"pointY":0.5}},"layers":[{"animations":[],"layers":[],"texturedRectangle":{"isBackgroundTexture":false,"singleTextureOpacity":1,"textureType":0,"textBaseline":0,"textXHeight":0,"isVerticalText":false},"initialState":{"affineTransform":[1,0,0,1,0,0],"masksToBounds":false,"rotation":0,"scale":1,"position":{"pointX":960,"pointY":540},"width":1920,"sublayerTransform":[1,0,0,0,0,1,0,0,0,0,1,0,0,0,0,1],"contentsRect":{"y":0,"x":0,"width":1,"height":1},"opacity":1,"edgeAntialiasingMask":0,"height":1080,"hidden":false,"anchorPoint":{"pointX":0.5,"pointY":0.5}},"texture":"700DB36790A0A0B19C6FC75F06CE45BB"},{"animations":[{"additive":false,"timeOffset":0,"beginTime":0,"from":{"scalar":false},"repeatCount":0,"fillMode":"both","duration":0.01,"autoreverses":false,"property":"hidden","to":{"scalar":true},"removedOnCompletion":false}],"layers":[],"texturedRectangle":{"isBackgroundTexture":false,"singleTextureOpacity":1,"textureType":0,"textBaseline":0,"textXHeight":0,"isVerticalText":false},"initialState":{"affineTransform":[1,0,0,1,0,0],"masksToBounds":false,"rotation":0,"scale":1,"position":{"pointX":960,"pointY":540},"width":1920,"sublayerTransform":[1,0,0,0,0,1,0,0,0,0,1,0,0,0,0,1],"contentsRect":{"y":0,"x":0,"width":1,"height":1},"opacity":1,"edgeAntialiasingMask":0,"height":1080,"hidden":false,"anchorPoint":{"pointX":0.5,"pointY":0.5}},"texture":"6A3B082A2ABCE3326AD9F0AF8CC0CB0A"}]}]},"effects":[],"duration":0.01,"type":"transition","attributes":{"direction":0},"name":"none","objectID":"0"}],"automaticPlay":false,"hyperlinks":[],"accessibility":[{"text":"mudanza1.gif","targetRectangle":{"y":242.44490051269531,"x":-56.723434448242188,"width":998.46417236328125,"height":561.6361083984375}},{"text":"SWAN","targetRectangle":{"y":17.811520528793331,"x":1887.6313705444336,"width":17.564895629882812,"height":44.925000000000004}},{"text":"GRANDPA quickly joins her to help out and we see them both, sleeves rolled up, carrying the planter to its new corner.as the DAUGHTER unboxes some living room decor.","targetRectangle":{"y":1019.7887272834778,"x":250.41001105308533,"width":1419.1799999999987,"height":23.41986083984375}},{"text":"Rebolución","targetRectangle":{"y":981.11347107887264,"x":1887.6313705444336,"width":17.564895629882812,"height":81.075000000000045}},{"text":"mudanza2.gif","targetRectangle":{"y":242.44490051269531,"x":930.3421630859375,"width":998.46417236328125,"height":561.6361083984375}}],"baseLayer":{"animations":[],"initialState":{"affineTransform":[1,0,0,1,0,0],"masksToBounds":false,"rotation":0,"scale":1,"position":{"pointX":960,"pointY":540},"width":1920,"sublayerTransform":[1,0,0,0,0,1,0,0,0,0,1,0,0,0,0,1],"contentsRect":{"y":0,"x":0,"width":1,"height":1},"opacity":1,"edgeAntialiasingMask":251658240,"height":1080,"hidden":false,"anchorPoint":{"pointX":0.5,"pointY":0.5}},"objectID":"0","layers":[{"animations":[],"initialState":{"affineTransform":[1,0,0,1,0,0],"masksToBounds":false,"rotation":0,"scale":1,"position":{"pointX":960,"pointY":540},"width":1920,"sublayerTransform":[1,0,0,0,0,1,0,0,0,0,1,-0.00035007912466775983,0,0,0,1],"contentsRect":{"y":0,"x":0,"width":1,"height":1},"opacity":1,"edgeAntialiasingMask":251658240,"height":1080,"hidden":false,"anchorPoint":{"pointX":0.5,"pointY":0.5}},"layers":[{"animations":[],"layers":[],"texturedRectangle":{"isBackgroundTexture":false,"singleTextureOpacity":1,"textureType":0,"textBaseline":0,"textXHeight":0,"isVerticalText":false},"initialState":{"affineTransform":[1,0,0,1,0,0],"masksToBounds":false,"rotation":0,"scale":1,"position":{"pointX":960,"pointY":540},"width":1920,"sublayerTransform":[1,0,0,0,0,1,0,0,0,0,1,0,0,0,0,1],"contentsRect":{"y":0,"x":0,"width":1,"height":1},"opacity":1,"edgeAntialiasingMask":0,"height":1080,"hidden":false,"anchorPoint":{"pointX":0.5,"pointY":0.5}},"texture":"6A3B082A2ABCE3326AD9F0AF8CC0CB0A"}]}]}}]}